odoo/addons/ddmrp/README.rst
odoo/addons/ddmrp/__init__.py
odoo/addons/ddmrp/__manifest__.py
odoo/addons/ddmrp/hooks.py
odoo/addons/ddmrp/data/decimal_precision_data.xml
odoo/addons/ddmrp/data/ir_cron.xml
odoo/addons/ddmrp/data/ir_sequence.xml
odoo/addons/ddmrp/data/product_adu_calculation_method_data.xml
odoo/addons/ddmrp/data/stock_buffer_profile_data.xml
odoo/addons/ddmrp/data/stock_buffer_profile_lead_time_data.xml
odoo/addons/ddmrp/data/stock_buffer_profile_variability_data.xml
odoo/addons/ddmrp/demo/ddmrp_demo_user.xml
odoo/addons/ddmrp/demo/mrp_bom_demo.xml
odoo/addons/ddmrp/demo/product_category_demo.xml
odoo/addons/ddmrp/demo/product_product_demo.xml
odoo/addons/ddmrp/demo/product_supplierinfo_demo.xml
odoo/addons/ddmrp/demo/res_partner_demo.xml
odoo/addons/ddmrp/demo/stock_buffer_demo.xml
odoo/addons/ddmrp/i18n/ddmrp.pot
odoo/addons/ddmrp/i18n/es.po
odoo/addons/ddmrp/i18n/fr.po
odoo/addons/ddmrp/i18n/id.po
odoo/addons/ddmrp/i18n/it.po
odoo/addons/ddmrp/i18n/zh_Hans.po
odoo/addons/ddmrp/migrations/13.0.1.19.0/post-migration.py
odoo/addons/ddmrp/models/__init__.py
odoo/addons/ddmrp/models/mrp_bom.py
odoo/addons/ddmrp/models/mrp_move.py
odoo/addons/ddmrp/models/mrp_production.py
odoo/addons/ddmrp/models/procurement_group.py
odoo/addons/ddmrp/models/product_adu_calculation_method.py
odoo/addons/ddmrp/models/product_product.py
odoo/addons/ddmrp/models/product_template.py
odoo/addons/ddmrp/models/purchase_order.py
odoo/addons/ddmrp/models/res_company.py
odoo/addons/ddmrp/models/stock_buffer.py
odoo/addons/ddmrp/models/stock_buffer_profile.py
odoo/addons/ddmrp/models/stock_buffer_profile_lead_time.py
odoo/addons/ddmrp/models/stock_buffer_profile_variability.py
odoo/addons/ddmrp/models/stock_move.py
odoo/addons/ddmrp/models/stock_move_line.py
odoo/addons/ddmrp/models/stock_picking.py
odoo/addons/ddmrp/models/stock_rule.py
odoo/addons/ddmrp/models/stock_warehouse.py
odoo/addons/ddmrp/readme/CONFIGURE.rst
odoo/addons/ddmrp/readme/CONTRIBUTORS.rst
odoo13_addon_ddmrp-13.0.1.34.0.dist-info/METADATA
odoo13_addon_ddmrp-13.0.1.34.0.dist-info/WHEEL
odoo13_addon_ddmrp-13.0.1.34.0.dist-info/top_level.txt
odoo13_addon_ddmrp-13.0.1.34.0.dist-info/RECORD
