Metadata-Version: 2.1
Name: odoo13-addon-ddmrp
Version: 13.0.1.34.0
Summary: Demand Driven Material Requirements Planning
Home-page: https://github.com/OCA/ddmrp
Author: ForgeFlow, Odoo Community Association (OCA)
Author-email: support@odoo-community.org
License: LGPL-3
Platform: UNKNOWN
Classifier: Programming Language :: Python
Classifier: Framework :: Odoo
Classifier: Framework :: Odoo :: 13.0
Classifier: License :: OSI Approved :: GNU Lesser General Public License v3 (LGPLv3)
Classifier: Development Status :: 4 - Beta
Requires-Python: >=3.5
Requires-Dist: odoo13-addon-base-cron-exclusion
Requires-Dist: odoo13-addon-mrp-multi-level
Requires-Dist: odoo13-addon-stock-demand-estimate
Requires-Dist: odoo13-addon-stock-helper
Requires-Dist: odoo13-addon-stock-warehouse-calendar
Requires-Dist: odoo13-addon-web-widget-bokeh-chart
Requires-Dist: odoo <13.1dev,>=13.0a
